[
  {
    "id": "vl_041",
    "text": "自動車の登録において、登録事項に変更があった際に交付される「自動車検査証」の記録等に関する事務を適正に行うための、国土交通大臣の権限について、正しいものはどれか。",
    "options": [
      "変更登録を怠った者に対し、直ちに罰金を徴収する権限",
      "自動車の所有権を自由に剥奪できる権限",
      "税金の納付を確認せずに登録を抹消する権限",
      "登録事項の正確性を期すため、当該自動車の提示を命ずることができる権限"
    ],
    "correctIndex": 3,
    "explanation": "国土交通大臣は、登録事項の確認等のため、必要があると認めるときは、自動車の提示を命ずることができます。",
    "subject": "registration",
    "difficulty": "C",
    "isEnabled": true
  },
  {
    "id": "vl_042",
    "text": "「移転登録」を申請しなければならない正当な事由として、正しいものはどれか。",
    "options": [
      "売買や譲渡により、自動車の所有者が変更されたとき",
      "使用者の住所が移転したとき",
      "車体の色が大幅に塗り替えられたとき",
      "自動車の有効期間が満了したとき"
    ],
    "correctIndex": 0,
    "explanation": "所有者の変更を伴う場合は「移転登録」が必要です。住所変更は「変更登録」です。",
    "subject": "registration",
    "difficulty": "B",
    "isEnabled": true
  },
  {
    "id": "vl_043",
    "text": "車両総重量8トン以上の貨物自動車について、新規検査を受けた後の最初の自動車検査証の有効期間はどれか。",
    "options": [
      "2年",
      "3年",
      "1年",
      "6ヶ月"
    ],
    "correctIndex": 2,
    "explanation": "大型貨物自動車（8トン以上）等は、新車登録時の初回検査であっても有効期間は1年です。",
    "subject": "inspection",
    "difficulty": "B",
    "isEnabled": true
  },
  {
    "id": "vl_044",
    "text": "事業用自動車の「3ヶ月定期点検整備」の実施義務に関する記述として、正しいものはどれか。",
    "options": [
      "運転者が自分の責任で行わなければならない",
      "自動車の使用者が自らの責任で行う義務がある",
      "整備工場に任せている場合は、事業者に責任はない",
      "運行管理者がすべて実作業を行う義務がある"
    ],
    "correctIndex": 1,
    "explanation": "法定点検の実施義務者は「自動車の使用者」です。実作業は委託できますが、責任は使用者にあります。",
    "subject": "maintenance",
    "difficulty": "B",
    "isEnabled": true
  },
  {
    "id": "vl_045",
    "text": "整備管理者の選任要件において、実務経験（2年以上）により選任されようとする者が受講すべき研修はどれか。",
    "options": [
      "運行管理者講習",
      "安全運転管理者研修",
      "選任前研修",
      "整備主任者研修"
    ],
    "correctIndex": 2,
    "explanation": "一・二・三級整備士資格を持たず、実務経験で選任される場合は選任前研修が必要です。",
    "subject": "maintenance_manager",
    "difficulty": "B",
    "isEnabled": true
  },
  {
    "id": "vl_046",
    "text": "保安基準において、車両総重量8トン以上等の大型貨物自動車に装着が義務付けられている「衝突被害軽減ブレーキ（AEBS）」の目的はどれか。",
    "options": [
      "衝突を物理的に回避し、または衝突時の被害を軽減するため",
      "運転者が居眠りをしても目的地に着くため",
      "ブレーキパッドの摩耗を完全にゼロにするため",
      "燃費を劇的に向上させるため"
    ],
    "correctIndex": 0,
    "explanation": "AEBSは衝突の恐れがある際に自動でブレーキを作動させ、被害を軽減することを目的としています。",
    "subject": "safety_standards",
    "difficulty": "A",
    "isEnabled": true
  },
  {
    "id": "vl_047",
    "text": "自動車の「長さ、幅又は高さ」を変更した際、構造等変更検査を受けなければならない基準として正しいものはどれか。",
    "options": [
      "長さが1cmでも変われば必ず受ける",
      "車検の有効期間内であれば受ける必要はない",
      "任意保険の更新時に言えばよい",
      "一定の範囲（長さ±3cm、幅±2cm、高さ±4cm等）を超える変更があった場合"
    ],
    "correctIndex": 3,
    "explanation": "軽微な変更（一定範囲内）を除き、寸法や構造の重要な変更には構造等変更検査が必要です。",
    "subject": "registration",
    "difficulty": "C",
    "isEnabled": true
  },
  {
    "id": "vl_048",
    "text": "事業用自動車の「日常点検」の実施内容として、保安基準に定められた項目に含まれないものはどれか。",
    "options": [
      "ブレーキペダルの踏みしろ",
      "ワイパーのゴムのメーカー名",
      "エンジンオイルの量",
      "タイヤの空気圧（目視）"
    ],
    "correctIndex": 1,
    "explanation": "消耗品のブランドやメーカー名は、安全点検の法定項目ではありません。",
    "subject": "maintenance",
    "difficulty": "A",
    "isEnabled": true
  },
  {
    "id": "vl_049",
    "text": "整備管理者の業務として、「日常点検の実施の確認」を行うタイミングはいつか。",
    "options": [
      "1週間に一度まとめて確認する",
      "1ヶ月に一度、記録簿をチェックする",
      "1日の運行の開始前",
      "車両が故障したときだけ確認する"
    ],
    "correctIndex": 2,
    "explanation": "事業用自動車の日常点検は、1日1回、運行開始前に行うことを確認しなければなりません。",
    "subject": "maintenance_manager",
    "difficulty": "A",
    "isEnabled": true
  },
  {
    "id": "vl_050",
    "text": "自動車の型式、車台番号、原動機の型式に変更があった場合、いつまでに変更登録の申請をしなければならないか。",
    "options": [
      "15日以内",
      "30日以内",
      "直ちに",
      "次の車検まで"
    ],
    "correctIndex": 0,
    "explanation": "型式や車台番号などの重要な変更があったときは、15日以内に変更登録の申請が必要です。",
    "subject": "registration",
    "difficulty": "B",
    "isEnabled": true
  },
  {
    "id": "vl_051",
    "text": "道路運送車両法の保安基準において、前面ガラスの可視光線透過率は何％以上でなければならないか。",
    "options": [
      "50%以上",
      "80%以上",
      "90%以上",
      "70%以上"
    ],
    "correctIndex": 3,
    "explanation": "前面ガラスおよび運転者席・助手席の側面ガラスは、可視光線の透過率が70%以上でなければなりません。",
    "subject": "safety_standards",
    "difficulty": "B",
    "isEnabled": true
  },
  {
    "id": "vl_052",
    "text": "自動車を「解体」したときに行う手続き（永久抹消登録）の期限はいつまでか。",
    "options": [
      "解体した日から30日以内",
      "次の車検が切れるまで",
      "いつでもよい",
      "解体した日から15日以内"
    ],
    "correctIndex": 3,
    "explanation": "自動車を滅失し、解体し、又は自動車として使用しなくなったときは、15日以内に永久抹消登録の申請が必要です。",
    "subject": "registration",
    "difficulty": "C",
    "isEnabled": true
  },
  {
    "id": "vl_053",
    "text": "登録自動車を売買し、その所有者を変更しようとするときに行う「移転登録」の申請先として正しいものはどれか。",
    "options": [
      "所轄の警察署",
      "市町村役場",
      "運輸支局（又は自動車検査登録事務所）",
      "軽自動車検査協会"
    ],
    "correctIndex": 2,
    "explanation": "登録自動車の所有権移転の手続きは、運輸支局等で行います。",
    "subject": "registration",
    "difficulty": "B",
    "isEnabled": true
  },
  {
    "id": "vl_054",
    "text": "整備管理者が車両の運行を停止させる（運行の可否を決定する）際の基準として、誤っているものはどれか。",
    "options": [
      "運転者の昨夜の睡眠時間が4時間だった場合",
      "制動装置に重大な不具合がある場合",
      "灯火類がすべて球切れしている場合",
      "タイヤにバーストの恐れがある著しい損傷がある場合"
    ],
    "correctIndex": 0,
    "explanation": "運転者の健康状態は「運行管理者」の判断基準です。整備管理者は「車両の状態」に基づき判断します。",
    "subject": "maintenance_manager",
    "difficulty": "B",
    "isEnabled": true
  },
  {
    "id": "vl_055",
    "text": "保安基準において、「尾灯（テールランプ）」の色について正しいものはどれか。",
    "options": [
      "白色",
      "赤色",
      "橙色",
      "黄色"
    ],
    "correctIndex": 1,
    "explanation": "夜間の視認性確保のため、尾灯の灯光の色は「赤色」と定められています。",
    "subject": "safety_standards",
    "difficulty": "A",
    "isEnabled": true
  },
  {
    "id": "vl_056",
    "text": "自動車の「車軸」にかかる荷重（軸重）の保安基準の最大値は、原則として何トンか。",
    "options": [
      "10トン",
      "5トン",
      "20トン",
      "25トン"
    ],
    "correctIndex": 0,
    "explanation": "道路保護等のため、一軸あたりの軸重は10トンを超えてはなりません。",
    "subject": "safety_standards",
    "difficulty": "C",
    "isEnabled": true
  },
  {
    "id": "vl_057",
    "text": "「自動車検査証（車検証）」の有効期間が切れた自動車を、検査のために回送しようとする際、必要なものはどれか。",
    "options": [
      "譲渡証明書",
      "特別な届出は不要",
      "整備管理者の許可証",
      "臨時運行許可（仮ナンバー）"
    ],
    "correctIndex": 3,
    "explanation": "有効期間満了車を公道走行させるには、市町村等から臨時運行許可を受ける必要があります。",
    "subject": "registration",
    "difficulty": "A",
    "isEnabled": true
  },
  {
    "id": "vl_058",
    "text": "「整備命令」を受けた者が、その命令に従わずに自動車を運行させた場合の罰則はどれか。",
    "options": [
      "口頭注意のみ",
      "次回の車検代が免除される",
      "自動車の使用停止や罰金等の対象になる",
      "特に規定はない"
    ],
    "correctIndex": 2,
    "explanation": "整備命令に従わない場合、使用停止処分や道路運送車両法違反による罰則が適用されます。",
    "subject": "safety_standards",
    "difficulty": "B",
    "isEnabled": true
  },
  {
    "id": "vl_059",
    "text": "「タイヤ」の空気圧が異常に低い状態で高速走行を続けた際、タイヤが波打つように変形する現象を何というか。",
    "options": [
      "ハイドロプレーニング現象",
      "スタンディングウェーブ現象",
      "フェード現象",
      "ベーパーロック現象"
    ],
    "correctIndex": 1,
    "explanation": "空気圧不足での高速走行は、タイヤ接地面より後ろ側が波打つ「スタンディングウェーブ現象」を引き起こし、バーストを招きます。",
    "subject": "maintenance",
    "difficulty": "A",
    "isEnabled": true
  },
  {
    "id": "vl_060",
    "text": "臨時運行許可（仮ナンバー）を受けた者が、期間満了後に番号標（ナンバー）を返納しなければならない期限はいつか。",
    "options": [
      "3日以内",
      "10日以内",
      "15日以内",
      "5日以内"
    ],
    "correctIndex": 3,
    "explanation": "臨時運行許可期間満了の日から5日以内に、番号標と許可証を返納しなければなりません。",
    "subject": "registration",
    "difficulty": "B",
    "isEnabled": true
  }
]
